ibmaemagic/__init__.py
ibmaemagic/contrib/__init__.py
ibmaemagic/contrib/ibm_object_storage_persistor.py
ibmaemagic/magic/__init__.py
ibmaemagic/magic/analytic_magic_client.py
ibmaemagic/magic/functions.py
ibmaemagic/sdk/__init__.py
ibmaemagic/sdk/analytics_engine_client.py
ibmaemagic-0.0.4.dist-info/LICENSE
ibmaemagic-0.0.4.dist-info/METADATA
ibmaemagic-0.0.4.dist-info/WHEEL
ibmaemagic-0.0.4.dist-info/top_level.txt
ibmaemagic-0.0.4.dist-info/zip-safe
ibmaemagic-0.0.4.dist-info/RECORD
